{
  "orientation": "Vertical",
  "nodeLayouts": {
    "inputs": {
      "x": 639.5,
      "y": 62,
      "index": -1
    },
    "outputs": {
      "x": 126,
      "y": 1272,
      "index": -1
    },
    "formatRewriteIntentInputs": {
      "x": 586,
      "y": 172,
      "height": 75,
      "index": 0
    },
    "rewriteIntent": {
      "x": 586,
      "y": 282,
      "height": 75,
      "index": 1
    },
    "extractSearchIntent": {
      "x": 641,
      "y": 392,
      "height": 75,
      "index": 2
    },
    "checkContent": {
      "x": 291,
      "y": 392,
      "height": 75,
      "index": 3
    },
    "safeResponse": {
      "x": 12,
      "y": 612,
      "height": 75,
      "index": 4
    },
    "querySearchResource": {
      "x": 580.5,
      "y": 502,
      "height": 75,
      "index": 5
    },
    "chunkDocuments": {
      "x": 575,
      "y": 612,
      "height": 75,
      "index": 6
    },
    "selectChunks": {
      "x": 458.5,
      "y": 722,
      "height": 75,
      "index": 7
    },
    "formatGenerateReplyInputs": {
      "x": 580,
      "y": 832,
      "height": 75,
      "index": 8
    },
    "shouldGenerateReply": {
      "x": 233.5,
      "y": 502,
      "height": 75,
      "index": 9
    },
    "generateReply": {
      "x": 292,
      "y": 942,
      "height": 75,
      "index": 10
    },
    "merge_responses": {
      "x": 126,
      "y": 1052,
      "height": 75,
      "index": 11
    },
    "stream": {
      "x": 126,
      "y": 1162,
      "height": 75,
      "index": 12
    }
  },
  "viewport": {
    "transformMatrix": [
      0.36199601668266723,
      0,
      0,
      0.36199601668266723,
      64.4213573970834,
      -116.37510139243034
    ]
  }
}